{
  "run_at_iso": "2025-08-30T17:59:56.950Z",
  "run_at_it": "30/08/2025 19:59:56 Europe/Rome",
  "timezone": "Europe/Rome",
  "locale": "it-IT",
  "events_count": 11,
  "events": [
    {
      "type": "SELL",
      "wallet": "C4Qh...8Pkt",
      "amount": 20698.105913,
      "tx": "5U114GDEkkR71wrNnuAuXi4TsRvCWXKZNug3aWBYn3DRDaHe7Ftf8t2ikVHRTKQoWsRzrR33fkboAUidcVrhzomF",
      "ts_iso": "2025-08-30T17:50:20.000Z",
      "ts_it": "30/08/2025 19:50:20 Europe/Rome"
    },
    {
      "type": "SELL",
      "wallet": "C4Qh...8Pkt",
      "amount": 20698.105913,
      "tx": "aBZQL6kYpemB9sFX49UNyEkRjSzMnrFAzA8W1o7nwDy9QaX47TiVukScG3khEV3nxnCaSNuMypP1j5tdwc4gnY6",
      "ts_iso": "2025-08-30T17:50:32.000Z",
      "ts_it": "30/08/2025 19:50:32 Europe/Rome"
    },
    {
      "type": "BUY",
      "wallet": "C4Qh...8Pkt",
      "amount": 80135.96588,
      "tx": "37ZcnGK8WpAn6EqvJWQicJGuUiA9HCBra7FcJQiBtAvsspVqBxjmfxxJn8fLiudXNmi91ghf6C2xjQF1t8ftM3sY",
      "ts_iso": "2025-08-30T17:50:47.000Z",
      "ts_it": "30/08/2025 19:50:47 Europe/Rome"
    },
    {
      "type": "SELL",
      "wallet": "4UQ2...TuXa",
      "amount": 13654.667567,
      "tx": "5WuYAQXUjZTNWwvaGuWX1JfJuFFz5GVJuJaAX4NNjMSVzEv5ouk32qa5K84HtFvmVef3HwhtK1LVCHkZ3wuA6HGE",
      "ts_iso": "2025-08-30T17:51:05.000Z",
      "ts_it": "30/08/2025 19:51:05 Europe/Rome"
    },
    {
      "type": "BUY",
      "wallet": "4UQ2...TuXa",
      "amount": 26502.700858,
      "tx": "3voebyxqeQTeogS1gdjF2w1m2tb9E8193sFHkoKiFAZ6ruQNNAJRbotFEJFG1zTePuG8pdQm6E9i5KqV2PtqWNp4",
      "ts_iso": "2025-08-30T17:53:28.000Z",
      "ts_it": "30/08/2025 19:53:28 Europe/Rome"
    },
    {
      "type": "SELL",
      "wallet": "4UQ2...TuXa",
      "amount": 13565.05702,
      "tx": "32sZXwchCYF2uK9N8GzB1XRQQP2vhnpnKmjD5RgFyh5oqZ7fYLsFNBKJ5qzkPFq9kC1uWoqXszqywk4XtjcaqvPk",
      "ts_iso": "2025-08-30T17:53:47.000Z",
      "ts_it": "30/08/2025 19:53:47 Europe/Rome"
    },
    {
      "type": "SELL",
      "wallet": "4UQ2...TuXa",
      "amount": 13570.372871,
      "tx": "3wKSXkgfKB7yfgH1Yx5idfTy6Af8rDqAeGVnYRJnyfAdnf3NBLwnhfRj6YyndT3X5HpQ8yE3bqneJYUTNWcCS6X",
      "ts_iso": "2025-08-30T17:54:18.000Z",
      "ts_it": "30/08/2025 19:54:18 Europe/Rome"
    },
    {
      "type": "SELL",
      "wallet": "4UQ2...TuXa",
      "amount": 13574.782956,
      "tx": "2VNvygeocug4m96jKocoGFmQ7ae7MFSWB4f92w2bseaSg39WYyKhhsBzJ7jR1Z8zDtA9TMvd2onrhfzxqxcTV8Zh",
      "ts_iso": "2025-08-30T17:56:18.000Z",
      "ts_it": "30/08/2025 19:56:18 Europe/Rome"
    },
    {
      "type": "BUY",
      "wallet": "4UQ2...TuXa",
      "amount": 26490.328867,
      "tx": "2UMiKZ6c8kyb3Ejy6txkTVvcpGv77NUU4gLxZxyzGUbfHM7LpcTTkFmofRuFpMTvEFsKSQ8jNgcwUvaXC3STmyqb",
      "ts_iso": "2025-08-30T17:57:24.000Z",
      "ts_it": "30/08/2025 19:57:24 Europe/Rome"
    },
    {
      "type": "SELL",
      "wallet": "4UQ2...TuXa",
      "amount": 13562.913187,
      "tx": "64H6Cd8nvMHJwDXw7vAbSJpHu1YR57Nmp6vvbmWEzs1j2FVpToX8S1RgfTzrahx79sZnGWuM6AtRvzLf292tbwHo",
      "ts_iso": "2025-08-30T17:57:46.000Z",
      "ts_it": "30/08/2025 19:57:46 Europe/Rome"
    },
    {
      "type": "SELL",
      "wallet": "4UQ2...TuXa",
      "amount": 13559.643725,
      "tx": "XWHhNADuWrSUvXa7CTPX5U2AJdm3vKFodc9JtKMn2JxVrwgba4WGpPfk79Yk31PG113VjMZgKivSStZRoLQRxtq",
      "ts_iso": "2025-08-30T17:58:06.000Z",
      "ts_it": "30/08/2025 19:58:06 Europe/Rome"
    }
  ]
}